vdaq_soap/__init__.py
vdaq_soap/analyzeHoldDelay.py
vdaq_soap/analyzeMbias.py
vdaq_soap/data_utils.py
vdaq_soap/maskNoisyChannels.py
vdaq_soap/soapCheckAliVATA.py
vdaq_soap/soapHoldDelay.py
vdaq_soap/soapMbias.py
vdaq_soap/soapTestChannel.py
vdaq_soap-1.1.4.dist-info/METADATA
vdaq_soap-1.1.4.dist-info/WHEEL
vdaq_soap-1.1.4.dist-info/entry_points.txt
vdaq_soap-1.1.4.dist-info/top_level.txt
vdaq_soap-1.1.4.dist-info/RECORD
