Metadata-Version: 2.4
Name: vdaq_soap
Version: 1.1.4
Summary: A collection of python scripts to control VDaq.
Author-email: Carlos Lacasta <carlos.lacasta@alibavasystems.com>
Project-URL: Homepage, https://igit.ific.uv.es
Project-URL: Bug Tracker, https://igit.ific.uv.es
Classifier: Programming Language :: Python :: 3
Classifier: Operating System :: OS Independent
Requires-Python: >=3.7
Requires-Dist: daqpp>=2.0.3
Requires-Dist: lmfit>=1.0.3
Requires-Dist: vdaq_ana>=0.0.0
Requires-Dist: matplotlib>=3.3.0
Requires-Dist: numpy>=1.19.0
Requires-Dist: python_docx>=0.8.11
